pymil.py
pymil-0.3.0.dist-info/METADATA
pymil-0.3.0.dist-info/WHEEL
pymil-0.3.0.dist-info/entry_points.txt
pymil-0.3.0.dist-info/licenses/LICENSE.txt
pymil-0.3.0.dist-info/RECORD
