Metadata-Version: 2.4
Name: pymil
Version: 0.3.0
Summary: A basic Open-source Carte internationale du Monde au Millionième nomenclature encoder.
Project-URL: Source, https://github.com/endarthur/pymil
Author-email: Arthur Endlein <endarthur@gmail.com>
License-Expression: GPL-3.0-or-later
License-File: LICENSE.txt
Keywords: GIS,cartography,maps
Classifier: Development Status :: 3 - Alpha
Classifier: License :: OSI Approved :: GNU General Public License v3 (GPLv3)
Classifier: Topic :: Scientific/Engineering :: GIS
Classifier: Topic :: Utilities
